[{"nodeId":"/ip4/209.44.107.2/tcp/39846/p2p/12D3KooWRUiQZ88oNWx4FvdUn1PQWPc9VkBMqgwFAByTPGmiZw6o","city":"Los Angeles,","version":"2.2.0","cpu":"i9-13900K/KF","disk":"4TB PS5 SSD固态硬盘 M.2","name":"node节点","logo":"http://test-123-q.bucket.foreverland.xyz/图标1.png","domain":"www.foreverland-node.com"},{"nodeId":"8c49bb02-dd62-4d15-9426-e1161a90704a","city":"Los Angeles,","version":"2.2.0","cpu":"i9-13900K/KF","disk":"4TB PS5 SSD固态硬盘 M.2","name":"node节点","logo":"http://test-123-q.bucket.foreverland.xyz/图标1.png","domain":"www.foreverland-node.com"},{"nodeId":"8c49bb02-dd62-4d15-9426-e1161a90704a","city":"Los Angeles,","version":"2.2.0","cpu":"i9-13900K/KF","disk":"4TB PS5 SSD固态硬盘 M.2","name":"node节点","logo":"","domain":"www.foreverland-node.com"}]
